utwrite/__init__.py
utwrite/auto_generate_test.py
utwrite/collector.py
utwrite/executor.py
utwrite/headers.py
utwrite/maya_unittest.py
utwrite/unittest_cases.py
utwrite/utilities.py
utwrite-0.0.15.dist-info/licenses/LICENSE
utwrite-0.0.15.dist-info/METADATA
utwrite-0.0.15.dist-info/WHEEL
utwrite-0.0.15.dist-info/entry_points.txt
utwrite-0.0.15.dist-info/top_level.txt
utwrite-0.0.15.dist-info/RECORD
