Metadata-Version: 2.4
Name: utwrite
Version: 0.0.15
Summary: Auto[magically] write Python unittest files from docstrings.
Project-URL: Homepage, https://codeberg.org/pbellini/utwrite
Classifier: Intended Audience :: Developers
Requires-Python: >=3.7
License-File: LICENSE
Dynamic: license-file
